equilibrator_assets/__init__.py
equilibrator_assets/chemaxon.py
equilibrator_assets/cli.py
equilibrator_assets/compounds.py
equilibrator_assets/generate_compound.py
equilibrator_assets/group_decompose.py
equilibrator_assets/groups.py
equilibrator_assets/local_compound_cache.py
equilibrator_assets/metanetx.py
equilibrator_assets/molecule.py
equilibrator_assets/registry.py
equilibrator_assets/thermodynamics.py
equilibrator_assets/data/__init__.py
equilibrator_assets/data/add_inchikeys.py
equilibrator_assets/data/magnesium_pkds.csv
equilibrator_assets/data/prefix_mapping.tsv
equilibrator_assets-0.6.0.dist-info/LICENSE
equilibrator_assets-0.6.0.dist-info/METADATA
equilibrator_assets-0.6.0.dist-info/WHEEL
equilibrator_assets-0.6.0.dist-info/top_level.txt
equilibrator_assets-0.6.0.dist-info/zip-safe
equilibrator_assets-0.6.0.dist-info/RECORD
