Metadata-Version: 2.1
Name: equilibrator-assets
Version: 0.6.0
Summary: Generate cache assets from MetaNetX content.
Author-email: Elad Noor <elad.noor@weizmann.ac.il>, "Moritz E. Beber" <midnighter@posteo.net>
License: MIT License
Project-URL: repository, https://gitlab.com/equilibrator/equilibrator-assets/
Project-URL: documentation, https://equilibrator.readthedocs.io/en/latest/
Keywords: component contribution,Gibbs energy,biochemical reaction,eQuilibrator
Classifier: Development Status :: 4 - Beta
Classifier: Intended Audience :: Science/Research
Classifier: Topic :: Scientific/Engineering :: Bio-Informatics
Classifier: Topic :: Scientific/Engineering :: Chemistry
Classifier: License :: OSI Approved :: MIT License
Classifier: Natural Language :: English
Classifier: Operating System :: OS Independent
Classifier: Programming Language :: Python :: 3 :: Only
Classifier: Programming Language :: Python :: 3.9
Classifier: Programming Language :: Python :: 3.10
Classifier: Programming Language :: Python :: 3.11
Classifier: Programming Language :: Python :: 3.12
Requires-Python: >=3.9
License-File: LICENSE
Requires-Dist: click
Requires-Dist: click-log
Requires-Dist: numpy
Requires-Dist: periodictable
Requires-Dist: python-dateutil
Requires-Dist: requests
Requires-Dist: equilibrator-api ~=0.6.0
Requires-Dist: equilibrator-cache ~=0.6.0
Requires-Dist: openbabel-wheel >=3.1.1.19
Provides-Extra: deployment
Requires-Dist: click ; extra == 'deployment'
Requires-Dist: click-log ; extra == 'deployment'
Requires-Dist: python-dateutil ; extra == 'deployment'
Requires-Dist: requests ; extra == 'deployment'
Requires-Dist: tqdm ; extra == 'deployment'
Provides-Extra: development
Requires-Dist: black ; extra == 'development'
Requires-Dist: isort ; extra == 'development'
Requires-Dist: flake8 ; extra == 'development'
Requires-Dist: safety ; extra == 'development'
Requires-Dist: tox ; extra == 'development'
Requires-Dist: twine ; extra == 'development'
Requires-Dist: jupyter ; extra == 'development'
Requires-Dist: jupyterlab ; extra == 'development'
Provides-Extra: test
Requires-Dist: pytest ; extra == 'test'
Requires-Dist: pytest-cov ; extra == 'test'
Requires-Dist: pytest-raises ; extra == 'test'
